exn/__init__.py
exn/__main__.py
exn/constant/__init__.py
exn/dao/__init__.py
exn/dto/__init__.py
exn/manager/__init__.py
exn/theme/__init__.py
exn/utils/__init__.py
exn/view/__init__.py
exn/view/about.py
exn/view/board.py
exn/view/footer.py
exn/view/front.py
exn/view/goto.py
exn/view/info.py
exn/view/past.py
exn/view/roll.py
exn/view/search.py
exn/view/switcher.py
exn/view/toc.py
exn/view/top.py
exn/view/util.py
tests/__init__.py
exn-0.0.11.dist-info/LICENSE
exn-0.0.11.dist-info/METADATA
exn-0.0.11.dist-info/WHEEL
exn-0.0.11.dist-info/entry_points.txt
exn-0.0.11.dist-info/top_level.txt
exn-0.0.11.dist-info/RECORD
