Metadata-Version: 2.1
Name: exn
Version: 0.0.11
Summary: Browse a dossier of exonotes
Home-page: https://github.com/pyrustic/exn
Author: Pyrustic Evangelist
Author-email: rusticalex@yahoo.com
Maintainer: Pyrustic Evangelist
Maintainer-email: rusticalex@yahoo.com
License: MIT
Keywords: application,pyrustic
Platform: UNKNOWN
Classifier: Programming Language :: Python :: 3
Classifier: License :: OSI Approved :: MIT License
Classifier: Operating System :: OS Independent
Requires-Python: >=3.5
License-File: LICENSE
Requires-Dist: exonote
Requires-Dist: jesth
Requires-Dist: suggestion
Requires-Dist: gaspium
Requires-Dist: viewstack
Requires-Dist: viewable
